{
  "data": [
    {
      "title": "DENEME",
      "text": "Bu bir Deneme Reposudur.",
      "repo": "https://github.com/hozansahin/deneme",
      "langs": [
        "GO",
        "ANGULAR"
      ]
    },
    {
      "title": "SUPERCHARGE",
      "text": "A web application to record and analyze your League of Legends champion mastery points.",
      "repo": "https://github.com/zekroTJA/supercharge",
      "langs": [
        "C#",
        "ANGULAR"
      ]
    },
    {
      "title": "YURI 2",
      "text": "A feature rich Discord sound board with web interface and a fully documented REST and web socket API.",
      "repo": "https://github.com/zekroTJA/yuri2",
      "langs": [
        "GO",
        "ANGULAR"
      ]
    },
    {
      "title": "MYRUNES.COM",
      "text": "Save your League of Legends Champion Runes without wasting (in-game) money.",
      "repo": "https://github.com/zekroTJA/myrunes",
      "langs": [
        "GO",
        "VUE"
      ]
    },
    {
      "title": "VCTR",
      "text": "Self hosted short link management tool for creating, managing and analyzing accesses on short links.",
      "repo": "https://github.com/zekroTJA/vctr",
      "langs": [
        "C#",
        "ANGULAR"
      ]
    },
    {
      "title": "TOKENTOOLSR",
      "text": "A slim web application to check the validity, status and meta data of Discord bot API tokens.",
      "repo": "https://github.com/zekroTJA/tokenToolsR",
      "langs": [
        "GO",
        "REACT"
      ]
    },
    {
      "title": "ITSFRIDAY",
      "text": "Twitter API application for spreading friday-happiness to your Twitter followers natively using the Twitter REST API.",
      "repo": "https://github.com/zekroTJA/itsfriday",
      "langs": [
        "PYTHON"
      ]
    },
    {
      "title": "PYTTER",
      "text": "An approach to build a twitter REST API wrapper in python.",
      "repo": "https://github.com/zekroTJA/pytter",
      "langs": [
        "PYTHON"
      ]
    }
  ]
}
